pylacrosse_ha/__init__.py
pylacrosse_ha/cli_tool.py
pylacrosse_ha/lacrosse_ha.py
pylacrosse_ha/version.py
tests/__init__.py
tests/test_lacrosse.py
pylacrosse_ha-230a7.dist-info/AUTHORS
pylacrosse_ha-230a7.dist-info/COPYING
pylacrosse_ha-230a7.dist-info/METADATA
pylacrosse_ha-230a7.dist-info/WHEEL
pylacrosse_ha-230a7.dist-info/entry_points.txt
pylacrosse_ha-230a7.dist-info/top_level.txt
pylacrosse_ha-230a7.dist-info/RECORD
