Metadata-Version: 2.1
Name: pylacrosse-ha
Version: 230a7
Summary: LaCrosse sensor library for ha
Home-page: https://github.com/cedrik9/pylacrosse_ha
Author: ceedrik09
Author-email: cedrik0@web.de
License: LGPLv2+
Classifier: Development Status :: 3 - Alpha
Classifier: Environment :: Console
Classifier: License :: OSI Approved :: GNU Lesser General Public License v2 or later (LGPLv2+)
Classifier: Natural Language :: English
Classifier: Operating System :: OS Independent
Classifier: Programming Language :: Python :: 2
Classifier: Programming Language :: Python :: 2.7
Classifier: Programming Language :: Python :: 3
Classifier: Programming Language :: Python :: 3.4
Classifier: Programming Language :: Python :: 3.5
Classifier: Programming Language :: Python :: 3.6
Classifier: Topic :: Software Development :: Libraries :: Python Modules
License-File: COPYING
License-File: AUTHORS
Requires-Dist: pyserial
